{
    "name": "Mortar and Pestle",
    "icon": "roots:mortar",
    "category": "apparatus",
    "priority": true,
    "advancement": "roots:root",
    "secret": true,
    "pages": [
      {
        "type": "text",
        "text": "Placed solidly in the world, up to five reagents can be added to it. Once they have been collected, applying the pestle by right-clicking will craft the desired output.$(br2)Recipes for the mortar & pestle can be found throughout the book. In addition, the pestle itself can be stored in an empty mortar."
      },
      {
        "type":"crafting",
        "recipe": "roots:pestle",
        "recipe2": "roots:mortar",
        "title": "Mortar & Pestle"
      }
    ]
  }