{
  "name": "Sylvan Armor",
  "icon": "roots:sylvan_chestplate",
  "category": "crafting_armor_tools",
  "read_by_default": true,
  "pages": [
    {
      "type": "text",
      "text": "Example."
    },
    {
      "title": "Sylvan Helmet",
      "type": "fey_crafting_template",
      "recipe": "sylvan_helmet"
    },
    {
      "title": "Sylvan Chestplate",
      "type": "fey_crafting_template",
      "recipe": "sylvan_chestplate"
    },
    {
      "title": "Sylvan Leggings",
      "type": "fey_crafting_template",
      "recipe": "sylvan_leggings"
    },
    {
      "title": "Sylvan Boots",
      "type": "fey_crafting_template",
      "recipe": "sylvan_boots"
    }
  ]
}