{
  "name": "Sky Soarer",
  "icon": "roots:spell_icon{spell_storage:{s:\"roots:spell_sky_soarer\"}}",
  "category": "spells",
  "read_by_default": true,
  "flag": "roots:spell_sky_soarer",
  "pages": [
    {
      "type": "text",
      "text": "Example"
    },
    {
      "type": "spell_template",
      "spell": "spell_sky_soarer"
    },
    {
      "type": "spell_modifier_template",
      "spell": "spell_sky_soarer",
      "modifier": "roots:slow_fall"
    },
    {
      "type": "spell_modifier_template",
      "spell": "spell_sky_soarer",
      "modifier": "roots:arboreal_bypass"
    },
    {
      "type": "spell_modifier_template",
      "spell": "spell_sky_soarer",
      "modifier": "roots:momentum"
    },
    {
      "type": "spell_modifier_template",
      "spell": "spell_sky_soarer",
      "modifier": "roots:verticality"
    },
    {
      "type": "spell_modifier_template",
      "spell": "spell_sky_soarer",
      "modifier": "roots:jaunt"
    },
    {
      "type": "spell_modifier_template",
      "spell": "spell_sky_soarer",
      "modifier": "roots:regenerative_sky"
    },
    {
      "type": "spell_modifier_template",
      "spell": "spell_sky_soarer",
      "modifier": "roots:chem_trails"
    },
    {
      "type": "spell_modifier_template",
      "spell": "spell_sky_soarer",
      "modifier": "roots:eternal_flame"
    },
    {
      "type": "spell_modifier_template",
      "spell": "spell_sky_soarer",
      "modifier": "roots:friendly_earth"
    },
    {
      "type": "spell_modifier_template",
      "spell": "spell_sky_soarer",
      "modifier": "roots:aquaplane"
    }

  ]
}